{
  "-67,57": {
    "SourceVersionHash": "rDbYOq+IUfQiOF1oAgcnYt/GkfM=",
    "VersionHash": "7Vx87Y9TdOkJEPlT0C3ZgizdUU0="
  },
  "-66,57": {
    "SourceVersionHash": "rDbYOq+IUfQiOF1oAgcnYt/GkfM=",
    "VersionHash": "7Vx87Y9TdOkJEPlT0C3ZgizdUU0="
  },
  "-67,58": {
    "SourceVersionHash": "rDbYOq+IUfQiOF1oAgcnYt/GkfM=",
    "VersionHash": "7Vx87Y9TdOkJEPlT0C3ZgizdUU0="
  },
  "-66,58": {
    "SourceVersionHash": "rDbYOq+IUfQiOF1oAgcnYt/GkfM=",
    "VersionHash": "7Vx87Y9TdOkJEPlT0C3ZgizdUU0="
  },
  "-66,56": {
    "SourceVersionHash": "rDbYOq+IUfQiOF1oAgcnYt/GkfM=",
    "VersionHash": "7Vx87Y9TdOkJEPlT0C3ZgizdUU0="
  },
  "-67,55": {
    "SourceVersionHash": "rDbYOq+IUfQiOF1oAgcnYt/GkfM=",
    "VersionHash": "7Vx87Y9TdOkJEPlT0C3ZgizdUU0="
  },
  "-66,55": {
    "SourceVersionHash": "rDbYOq+IUfQiOF1oAgcnYt/GkfM=",
    "VersionHash": "7Vx87Y9TdOkJEPlT0C3ZgizdUU0="
  },
  "-67,56": {
    "SourceVersionHash": "rDbYOq+IUfQiOF1oAgcnYt/GkfM=",
    "VersionHash": "7Vx87Y9TdOkJEPlT0C3ZgizdUU0="
  },
  "-68,57": {
    "SourceVersionHash": "rDbYOq+IUfQiOF1oAgcnYt/GkfM=",
    "VersionHash": "7Vx87Y9TdOkJEPlT0C3ZgizdUU0="
  },
  "-69,57": {
    "SourceVersionHash": "rDbYOq+IUfQiOF1oAgcnYt/GkfM=",
    "VersionHash": "7Vx87Y9TdOkJEPlT0C3ZgizdUU0="
  },
  "-68,56": {
    "SourceVersionHash": "rDbYOq+IUfQiOF1oAgcnYt/GkfM=",
    "VersionHash": "7Vx87Y9TdOkJEPlT0C3ZgizdUU0="
  },
  "-68,55": {
    "SourceVersionHash": "rDbYOq+IUfQiOF1oAgcnYt/GkfM=",
    "VersionHash": "7Vx87Y9TdOkJEPlT0C3ZgizdUU0="
  },
  "-69,56": {
    "SourceVersionHash": "rDbYOq+IUfQiOF1oAgcnYt/GkfM=",
    "VersionHash": "7Vx87Y9TdOkJEPlT0C3ZgizdUU0="
  },
  "-69,58": {
    "SourceVersionHash": "rDbYOq+IUfQiOF1oAgcnYt/GkfM=",
    "VersionHash": "7Vx87Y9TdOkJEPlT0C3ZgizdUU0="
  },
  "-68,58": {
    "SourceVersionHash": "rDbYOq+IUfQiOF1oAgcnYt/GkfM=",
    "VersionHash": "7Vx87Y9TdOkJEPlT0C3ZgizdUU0="
  },
  "-65,57": {
    "SourceVersionHash": "rDbYOq+IUfQiOF1oAgcnYt/GkfM=",
    "VersionHash": "7Vx87Y9TdOkJEPlT0C3ZgizdUU0="
  },
  "-64,57": {
    "SourceVersionHash": "rDbYOq+IUfQiOF1oAgcnYt/GkfM=",
    "VersionHash": "7Vx87Y9TdOkJEPlT0C3ZgizdUU0="
  },
  "-65,58": {
    "SourceVersionHash": "rDbYOq+IUfQiOF1oAgcnYt/GkfM=",
    "VersionHash": "7Vx87Y9TdOkJEPlT0C3ZgizdUU0="
  },
  "-64,58": {
    "SourceVersionHash": "rDbYOq+IUfQiOF1oAgcnYt/GkfM=",
    "VersionHash": "7Vx87Y9TdOkJEPlT0C3ZgizdUU0="
  },
  "-66,59": {
    "SourceVersionHash": "rDbYOq+IUfQiOF1oAgcnYt/GkfM=",
    "VersionHash": "7Vx87Y9TdOkJEPlT0C3ZgizdUU0="
  },
  "-67,59": {
    "SourceVersionHash": "rDbYOq+IUfQiOF1oAgcnYt/GkfM=",
    "VersionHash": "7Vx87Y9TdOkJEPlT0C3ZgizdUU0="
  },
  "-69,59": {
    "SourceVersionHash": "rDbYOq+IUfQiOF1oAgcnYt/GkfM=",
    "VersionHash": "7Vx87Y9TdOkJEPlT0C3ZgizdUU0="
  },
  "-68,59": {
    "SourceVersionHash": "rDbYOq+IUfQiOF1oAgcnYt/GkfM=",
    "VersionHash": "7Vx87Y9TdOkJEPlT0C3ZgizdUU0="
  },
  "-65,55": {
    "SourceVersionHash": "rDbYOq+IUfQiOF1oAgcnYt/GkfM=",
    "VersionHash": "7Vx87Y9TdOkJEPlT0C3ZgizdUU0="
  },
  "-64,55": {
    "SourceVersionHash": "1Y7b7F142apxQOh+8Cf4AoUWhAQ=",
    "VersionHash": "7Vx87Y9TdOkJEPlT0C3ZgizdUU0="
  },
  "-65,56": {
    "SourceVersionHash": "rDbYOq+IUfQiOF1oAgcnYt/GkfM=",
    "VersionHash": "7Vx87Y9TdOkJEPlT0C3ZgizdUU0="
  },
  "-64,56": {
    "SourceVersionHash": "rDbYOq+IUfQiOF1oAgcnYt/GkfM=",
    "VersionHash": "7Vx87Y9TdOkJEPlT0C3ZgizdUU0="
  },
  "-65,59": {
    "SourceVersionHash": "rDbYOq+IUfQiOF1oAgcnYt/GkfM=",
    "VersionHash": "YirkFFI3c3J25JJI3Ix/PXnE60I="
  },
  "-64,59": {
    "SourceVersionHash": "rDbYOq+IUfQiOF1oAgcnYt/GkfM=",
    "VersionHash": "YirkFFI3c3J25JJI3Ix/PXnE60I="
  },
  "-66,54": {
    "SourceVersionHash": "rDbYOq+IUfQiOF1oAgcnYt/GkfM=",
    "VersionHash": "UR5rP8i6o+h7PC15TNcBWNsaRRE="
  },
  "-66,53": {
    "SourceVersionHash": "rDbYOq+IUfQiOF1oAgcnYt/GkfM=",
    "VersionHash": "UR5rP8i6o+h7PC15TNcBWNsaRRE="
  },
  "-67,54": {
    "SourceVersionHash": "rDbYOq+IUfQiOF1oAgcnYt/GkfM=",
    "VersionHash": "UR5rP8i6o+h7PC15TNcBWNsaRRE="
  },
  "-67,53": {
    "SourceVersionHash": "rDbYOq+IUfQiOF1oAgcnYt/GkfM=",
    "VersionHash": "UR5rP8i6o+h7PC15TNcBWNsaRRE="
  },
  "-67,52": {
    "SourceVersionHash": "rDbYOq+IUfQiOF1oAgcnYt/GkfM=",
    "VersionHash": "UR5rP8i6o+h7PC15TNcBWNsaRRE="
  },
  "-66,52": {
    "SourceVersionHash": "rDbYOq+IUfQiOF1oAgcnYt/GkfM=",
    "VersionHash": "UR5rP8i6o+h7PC15TNcBWNsaRRE="
  },
  "-68,53": {
    "SourceVersionHash": "rDbYOq+IUfQiOF1oAgcnYt/GkfM=",
    "VersionHash": "UR5rP8i6o+h7PC15TNcBWNsaRRE="
  },
  "-68,54": {
    "SourceVersionHash": "rDbYOq+IUfQiOF1oAgcnYt/GkfM=",
    "VersionHash": "UR5rP8i6o+h7PC15TNcBWNsaRRE="
  },
  "-68,52": {
    "SourceVersionHash": "rDbYOq+IUfQiOF1oAgcnYt/GkfM=",
    "VersionHash": "UR5rP8i6o+h7PC15TNcBWNsaRRE="
  },
  "-64,53": {
    "SourceVersionHash": "1Y7b7F142apxQOh+8Cf4AoUWhAQ=",
    "VersionHash": "UR5rP8i6o+h7PC15TNcBWNsaRRE="
  },
  "-65,53": {
    "SourceVersionHash": "rDbYOq+IUfQiOF1oAgcnYt/GkfM=",
    "VersionHash": "UR5rP8i6o+h7PC15TNcBWNsaRRE="
  },
  "-64,54": {
    "SourceVersionHash": "1Y7b7F142apxQOh+8Cf4AoUWhAQ=",
    "VersionHash": "zwxha/vZ8W5ONwYbk2Cub3WNDHs="
  },
  "-65,54": {
    "SourceVersionHash": "rDbYOq+IUfQiOF1oAgcnYt/GkfM=",
    "VersionHash": "zwxha/vZ8W5ONwYbk2Cub3WNDHs="
  },
  "-64,51": {
    "SourceVersionHash": "rDbYOq+IUfQiOF1oAgcnYt/GkfM=",
    "VersionHash": "zwxha/vZ8W5ONwYbk2Cub3WNDHs="
  },
  "-65,52": {
    "SourceVersionHash": "rDbYOq+IUfQiOF1oAgcnYt/GkfM=",
    "VersionHash": "zwxha/vZ8W5ONwYbk2Cub3WNDHs="
  },
  "-64,52": {
    "SourceVersionHash": "1Y7b7F142apxQOh+8Cf4AoUWhAQ=",
    "VersionHash": "zwxha/vZ8W5ONwYbk2Cub3WNDHs="
  },
  "-62,59": {
    "SourceVersionHash": "rDbYOq+IUfQiOF1oAgcnYt/GkfM=",
    "VersionHash": "DVvf7Sa4uY8SmXLlW7bA1HxrVL0="
  },
  "-63,59": {
    "SourceVersionHash": "rDbYOq+IUfQiOF1oAgcnYt/GkfM=",
    "VersionHash": "DVvf7Sa4uY8SmXLlW7bA1HxrVL0="
  },
  "-61,59": {
    "SourceVersionHash": "rDbYOq+IUfQiOF1oAgcnYt/GkfM=",
    "VersionHash": "DVvf7Sa4uY8SmXLlW7bA1HxrVL0="
  },
  "-70,58": {
    "SourceVersionHash": "rDbYOq+IUfQiOF1oAgcnYt/GkfM=",
    "VersionHash": "Zksn5kENHOx+WOQKUrZazY8wovQ="
  },
  "-70,57": {
    "SourceVersionHash": "rDbYOq+IUfQiOF1oAgcnYt/GkfM=",
    "VersionHash": "Zksn5kENHOx+WOQKUrZazY8wovQ="
  },
  "-70,56": {
    "SourceVersionHash": "rDbYOq+IUfQiOF1oAgcnYt/GkfM=",
    "VersionHash": "Zksn5kENHOx+WOQKUrZazY8wovQ="
  },
  "-70,59": {
    "SourceVersionHash": "rDbYOq+IUfQiOF1oAgcnYt/GkfM=",
    "VersionHash": "Zksn5kENHOx+WOQKUrZazY8wovQ="
  },
  "-61,50": {
    "SourceVersionHash": "rDbYOq+IUfQiOF1oAgcnYt/GkfM=",
    "VersionHash": "Zksn5kENHOx+WOQKUrZazY8wovQ="
  },
  "-61,52": {
    "SourceVersionHash": "1Y7b7F142apxQOh+8Cf4AoUWhAQ=",
    "VersionHash": "nUwq0SuOIDz7rJ/BBv+icAO192w="
  },
  "-61,51": {
    "SourceVersionHash": "rDbYOq+IUfQiOF1oAgcnYt/GkfM=",
    "VersionHash": "nUwq0SuOIDz7rJ/BBv+icAO192w="
  },
  "-61,57": {
    "SourceVersionHash": "rDbYOq+IUfQiOF1oAgcnYt/GkfM=",
    "VersionHash": "0GPpqhs08yuGtHNS3CGZk5NvPSA="
  },
  "-61,58": {
    "SourceVersionHash": "rDbYOq+IUfQiOF1oAgcnYt/GkfM=",
    "VersionHash": "0GPpqhs08yuGtHNS3CGZk5NvPSA="
  },
  "-63,57": {
    "SourceVersionHash": "rDbYOq+IUfQiOF1oAgcnYt/GkfM=",
    "VersionHash": "rggAo7rox88rqceLokA92Y2NqtM="
  },
  "-62,57": {
    "SourceVersionHash": "rDbYOq+IUfQiOF1oAgcnYt/GkfM=",
    "VersionHash": "rggAo7rox88rqceLokA92Y2NqtM="
  },
  "-63,58": {
    "SourceVersionHash": "rDbYOq+IUfQiOF1oAgcnYt/GkfM=",
    "VersionHash": "rggAo7rox88rqceLokA92Y2NqtM="
  },
  "-62,58": {
    "SourceVersionHash": "rDbYOq+IUfQiOF1oAgcnYt/GkfM=",
    "VersionHash": "rggAo7rox88rqceLokA92Y2NqtM="
  },
  "-61,53": {
    "SourceVersionHash": "1Y7b7F142apxQOh+8Cf4AoUWhAQ=",
    "VersionHash": "o32s9Niwt26FSsGEcAQFRJXW2fg="
  },
  "-63,55": {
    "SourceVersionHash": "1Y7b7F142apxQOh+8Cf4AoUWhAQ=",
    "VersionHash": "o32s9Niwt26FSsGEcAQFRJXW2fg="
  },
  "-61,54": {
    "SourceVersionHash": "1Y7b7F142apxQOh+8Cf4AoUWhAQ=",
    "VersionHash": "o32s9Niwt26FSsGEcAQFRJXW2fg="
  },
  "-62,55": {
    "SourceVersionHash": "1Y7b7F142apxQOh+8Cf4AoUWhAQ=",
    "VersionHash": "o32s9Niwt26FSsGEcAQFRJXW2fg="
  },
  "-61,55": {
    "SourceVersionHash": "1Y7b7F142apxQOh+8Cf4AoUWhAQ=",
    "VersionHash": "o32s9Niwt26FSsGEcAQFRJXW2fg="
  },
  "-61,56": {
    "SourceVersionHash": "rDbYOq+IUfQiOF1oAgcnYt/GkfM=",
    "VersionHash": "o32s9Niwt26FSsGEcAQFRJXW2fg="
  },
  "-62,56": {
    "SourceVersionHash": "rDbYOq+IUfQiOF1oAgcnYt/GkfM=",
    "VersionHash": "o32s9Niwt26FSsGEcAQFRJXW2fg="
  },
  "-63,56": {
    "SourceVersionHash": "rDbYOq+IUfQiOF1oAgcnYt/GkfM=",
    "VersionHash": "o32s9Niwt26FSsGEcAQFRJXW2fg="
  },
  "-62,50": {
    "SourceVersionHash": "rDbYOq+IUfQiOF1oAgcnYt/GkfM=",
    "VersionHash": "Emc9NjJ6LZC4LfSKotCr4ao73fY="
  },
  "-64,50": {
    "SourceVersionHash": "rDbYOq+IUfQiOF1oAgcnYt/GkfM=",
    "VersionHash": "Emc9NjJ6LZC4LfSKotCr4ao73fY="
  },
  "-63,50": {
    "SourceVersionHash": "rDbYOq+IUfQiOF1oAgcnYt/GkfM=",
    "VersionHash": "Emc9NjJ6LZC4LfSKotCr4ao73fY="
  },
  "-63,51": {
    "SourceVersionHash": "rDbYOq+IUfQiOF1oAgcnYt/GkfM=",
    "VersionHash": "vEkqN2+TMS0ozvlfEQM1seO1bgQ="
  },
  "-63,52": {
    "SourceVersionHash": "1Y7b7F142apxQOh+8Cf4AoUWhAQ=",
    "VersionHash": "vEkqN2+TMS0ozvlfEQM1seO1bgQ="
  },
  "-62,53": {
    "SourceVersionHash": "1Y7b7F142apxQOh+8Cf4AoUWhAQ=",
    "VersionHash": "vEkqN2+TMS0ozvlfEQM1seO1bgQ="
  },
  "-62,51": {
    "SourceVersionHash": "rDbYOq+IUfQiOF1oAgcnYt/GkfM=",
    "VersionHash": "vEkqN2+TMS0ozvlfEQM1seO1bgQ="
  },
  "-62,54": {
    "SourceVersionHash": "1Y7b7F142apxQOh+8Cf4AoUWhAQ=",
    "VersionHash": "vEkqN2+TMS0ozvlfEQM1seO1bgQ="
  },
  "-63,53": {
    "SourceVersionHash": "1Y7b7F142apxQOh+8Cf4AoUWhAQ=",
    "VersionHash": "vEkqN2+TMS0ozvlfEQM1seO1bgQ="
  },
  "-63,54": {
    "SourceVersionHash": "1Y7b7F142apxQOh+8Cf4AoUWhAQ=",
    "VersionHash": "vEkqN2+TMS0ozvlfEQM1seO1bgQ="
  },
  "-62,52": {
    "SourceVersionHash": "1Y7b7F142apxQOh+8Cf4AoUWhAQ=",
    "VersionHash": "vEkqN2+TMS0ozvlfEQM1seO1bgQ="
  }
}