{
  "110,-110": {
    "SourceVersionHash": "3bjhgdseJoX465Pt7K/3+eSt0dQ=",
    "VersionHash": "c8x6x22rTnJoacLs4otJHoN/ljY="
  },
  "111,-110": {
    "SourceVersionHash": "3bjhgdseJoX465Pt7K/3+eSt0dQ=",
    "VersionHash": "c8x6x22rTnJoacLs4otJHoN/ljY="
  },
  "111,-109": {
    "SourceVersionHash": "3bjhgdseJoX465Pt7K/3+eSt0dQ=",
    "VersionHash": "c8x6x22rTnJoacLs4otJHoN/ljY="
  },
  "110,-109": {
    "SourceVersionHash": "3bjhgdseJoX465Pt7K/3+eSt0dQ=",
    "VersionHash": "c8x6x22rTnJoacLs4otJHoN/ljY="
  }
}