{
  "21,-127": {
    "SourceVersionHash": "3bjhgdseJoX465Pt7K/3+eSt0dQ=",
    "VersionHash": "pX/Yxn1CePWP1FNeaUqVLgEPCmk="
  },
  "23,-127": {
    "SourceVersionHash": "3bjhgdseJoX465Pt7K/3+eSt0dQ=",
    "VersionHash": "pX/Yxn1CePWP1FNeaUqVLgEPCmk="
  },
  "22,-127": {
    "SourceVersionHash": "3bjhgdseJoX465Pt7K/3+eSt0dQ=",
    "VersionHash": "pX/Yxn1CePWP1FNeaUqVLgEPCmk="
  },
  "20,-127": {
    "SourceVersionHash": "3bjhgdseJoX465Pt7K/3+eSt0dQ=",
    "VersionHash": "pX/Yxn1CePWP1FNeaUqVLgEPCmk="
  },
  "23,-126": {
    "SourceVersionHash": "3bjhgdseJoX465Pt7K/3+eSt0dQ=",
    "VersionHash": "pX/Yxn1CePWP1FNeaUqVLgEPCmk="
  },
  "21,-126": {
    "SourceVersionHash": "3bjhgdseJoX465Pt7K/3+eSt0dQ=",
    "VersionHash": "pX/Yxn1CePWP1FNeaUqVLgEPCmk="
  },
  "22,-126": {
    "SourceVersionHash": "3bjhgdseJoX465Pt7K/3+eSt0dQ=",
    "VersionHash": "pX/Yxn1CePWP1FNeaUqVLgEPCmk="
  },
  "20,-126": {
    "SourceVersionHash": "3bjhgdseJoX465Pt7K/3+eSt0dQ=",
    "VersionHash": "pX/Yxn1CePWP1FNeaUqVLgEPCmk="
  },
  "21,-128": {
    "SourceVersionHash": "3bjhgdseJoX465Pt7K/3+eSt0dQ=",
    "VersionHash": "pX/Yxn1CePWP1FNeaUqVLgEPCmk="
  },
  "22,-128": {
    "SourceVersionHash": "3bjhgdseJoX465Pt7K/3+eSt0dQ=",
    "VersionHash": "pX/Yxn1CePWP1FNeaUqVLgEPCmk="
  },
  "20,-128": {
    "SourceVersionHash": "3bjhgdseJoX465Pt7K/3+eSt0dQ=",
    "VersionHash": "pX/Yxn1CePWP1FNeaUqVLgEPCmk="
  },
  "22,-125": {
    "SourceVersionHash": "3bjhgdseJoX465Pt7K/3+eSt0dQ=",
    "VersionHash": "/WiSlheL3hM07ClsPmwaQcOcdCQ="
  },
  "23,-125": {
    "SourceVersionHash": "3bjhgdseJoX465Pt7K/3+eSt0dQ=",
    "VersionHash": "/WiSlheL3hM07ClsPmwaQcOcdCQ="
  },
  "21,-125": {
    "SourceVersionHash": "3bjhgdseJoX465Pt7K/3+eSt0dQ=",
    "VersionHash": "/WiSlheL3hM07ClsPmwaQcOcdCQ="
  },
  "20,-125": {
    "SourceVersionHash": "3bjhgdseJoX465Pt7K/3+eSt0dQ=",
    "VersionHash": "/WiSlheL3hM07ClsPmwaQcOcdCQ="
  },
  "23,-128": {
    "SourceVersionHash": "3bjhgdseJoX465Pt7K/3+eSt0dQ=",
    "VersionHash": "/WiSlheL3hM07ClsPmwaQcOcdCQ="
  }
}