{
  "105,-53": {
    "SourceVersionHash": "i56H2hxFRAiNSTcl09jdxRDaZr8=",
    "VersionHash": "81Vqo+tVsHKjUXDqBvbdSOzXzI4="
  },
  "105,-55": {
    "SourceVersionHash": "i56H2hxFRAiNSTcl09jdxRDaZr8=",
    "VersionHash": "81Vqo+tVsHKjUXDqBvbdSOzXzI4="
  },
  "106,-53": {
    "SourceVersionHash": "i56H2hxFRAiNSTcl09jdxRDaZr8=",
    "VersionHash": "81Vqo+tVsHKjUXDqBvbdSOzXzI4="
  },
  "105,-56": {
    "SourceVersionHash": "i56H2hxFRAiNSTcl09jdxRDaZr8=",
    "VersionHash": "81Vqo+tVsHKjUXDqBvbdSOzXzI4="
  },
  "106,-56": {
    "SourceVersionHash": "i56H2hxFRAiNSTcl09jdxRDaZr8=",
    "VersionHash": "81Vqo+tVsHKjUXDqBvbdSOzXzI4="
  },
  "105,-54": {
    "SourceVersionHash": "i56H2hxFRAiNSTcl09jdxRDaZr8=",
    "VersionHash": "81Vqo+tVsHKjUXDqBvbdSOzXzI4="
  },
  "106,-55": {
    "SourceVersionHash": "i56H2hxFRAiNSTcl09jdxRDaZr8=",
    "VersionHash": "81Vqo+tVsHKjUXDqBvbdSOzXzI4="
  },
  "106,-54": {
    "SourceVersionHash": "i56H2hxFRAiNSTcl09jdxRDaZr8=",
    "VersionHash": "81Vqo+tVsHKjUXDqBvbdSOzXzI4="
  },
  "107,-54": {
    "SourceVersionHash": "i56H2hxFRAiNSTcl09jdxRDaZr8=",
    "VersionHash": "81Vqo+tVsHKjUXDqBvbdSOzXzI4="
  },
  "104,-53": {
    "SourceVersionHash": "i56H2hxFRAiNSTcl09jdxRDaZr8=",
    "VersionHash": "81Vqo+tVsHKjUXDqBvbdSOzXzI4="
  },
  "107,-55": {
    "SourceVersionHash": "i56H2hxFRAiNSTcl09jdxRDaZr8=",
    "VersionHash": "81Vqo+tVsHKjUXDqBvbdSOzXzI4="
  },
  "107,-56": {
    "SourceVersionHash": "i56H2hxFRAiNSTcl09jdxRDaZr8=",
    "VersionHash": "81Vqo+tVsHKjUXDqBvbdSOzXzI4="
  },
  "104,-54": {
    "SourceVersionHash": "i56H2hxFRAiNSTcl09jdxRDaZr8=",
    "VersionHash": "81Vqo+tVsHKjUXDqBvbdSOzXzI4="
  },
  "104,-55": {
    "SourceVersionHash": "i56H2hxFRAiNSTcl09jdxRDaZr8=",
    "VersionHash": "81Vqo+tVsHKjUXDqBvbdSOzXzI4="
  },
  "107,-53": {
    "SourceVersionHash": "i56H2hxFRAiNSTcl09jdxRDaZr8=",
    "VersionHash": "81Vqo+tVsHKjUXDqBvbdSOzXzI4="
  },
  "104,-56": {
    "SourceVersionHash": "i56H2hxFRAiNSTcl09jdxRDaZr8=",
    "VersionHash": "81Vqo+tVsHKjUXDqBvbdSOzXzI4="
  }
}