{
  "-88,-80": {
    "SourceVersionHash": "1Y7b7F142apxQOh+8Cf4AoUWhAQ=",
    "VersionHash": "89ng8pHYXhZFEypC/aqQlsXymnc="
  },
  "-86,-80": {
    "SourceVersionHash": "1Y7b7F142apxQOh+8Cf4AoUWhAQ=",
    "VersionHash": "89ng8pHYXhZFEypC/aqQlsXymnc="
  },
  "-87,-80": {
    "SourceVersionHash": "1Y7b7F142apxQOh+8Cf4AoUWhAQ=",
    "VersionHash": "89ng8pHYXhZFEypC/aqQlsXymnc="
  },
  "-85,-80": {
    "SourceVersionHash": "1Y7b7F142apxQOh+8Cf4AoUWhAQ=",
    "VersionHash": "89ng8pHYXhZFEypC/aqQlsXymnc="
  },
  "-87,-79": {
    "SourceVersionHash": "1Y7b7F142apxQOh+8Cf4AoUWhAQ=",
    "VersionHash": "89ng8pHYXhZFEypC/aqQlsXymnc="
  },
  "-86,-79": {
    "SourceVersionHash": "1Y7b7F142apxQOh+8Cf4AoUWhAQ=",
    "VersionHash": "89ng8pHYXhZFEypC/aqQlsXymnc="
  },
  "-85,-79": {
    "SourceVersionHash": "1Y7b7F142apxQOh+8Cf4AoUWhAQ=",
    "VersionHash": "89ng8pHYXhZFEypC/aqQlsXymnc="
  },
  "-88,-78": {
    "SourceVersionHash": "1Y7b7F142apxQOh+8Cf4AoUWhAQ=",
    "VersionHash": "89ng8pHYXhZFEypC/aqQlsXymnc="
  },
  "-86,-78": {
    "SourceVersionHash": "1Y7b7F142apxQOh+8Cf4AoUWhAQ=",
    "VersionHash": "89ng8pHYXhZFEypC/aqQlsXymnc="
  },
  "-85,-78": {
    "SourceVersionHash": "1Y7b7F142apxQOh+8Cf4AoUWhAQ=",
    "VersionHash": "89ng8pHYXhZFEypC/aqQlsXymnc="
  },
  "-86,-77": {
    "SourceVersionHash": "1Y7b7F142apxQOh+8Cf4AoUWhAQ=",
    "VersionHash": "89ng8pHYXhZFEypC/aqQlsXymnc="
  },
  "-87,-78": {
    "SourceVersionHash": "1Y7b7F142apxQOh+8Cf4AoUWhAQ=",
    "VersionHash": "89ng8pHYXhZFEypC/aqQlsXymnc="
  },
  "-88,-79": {
    "SourceVersionHash": "1Y7b7F142apxQOh+8Cf4AoUWhAQ=",
    "VersionHash": "89ng8pHYXhZFEypC/aqQlsXymnc="
  },
  "-87,-77": {
    "SourceVersionHash": "1Y7b7F142apxQOh+8Cf4AoUWhAQ=",
    "VersionHash": "89ng8pHYXhZFEypC/aqQlsXymnc="
  },
  "-88,-77": {
    "SourceVersionHash": "1Y7b7F142apxQOh+8Cf4AoUWhAQ=",
    "VersionHash": "89ng8pHYXhZFEypC/aqQlsXymnc="
  },
  "-85,-77": {
    "SourceVersionHash": "1Y7b7F142apxQOh+8Cf4AoUWhAQ=",
    "VersionHash": "6/GSDsBAiOAlQgJc+jrhI+6rR44="
  }
}