{
  "133,121": {
    "SourceVersionHash": "1Y7b7F142apxQOh+8Cf4AoUWhAQ=",
    "VersionHash": "n9tKcnRK3dUYdXPEWFB1FlAn6ac="
  },
  "135,121": {
    "SourceVersionHash": "1Y7b7F142apxQOh+8Cf4AoUWhAQ=",
    "VersionHash": "n9tKcnRK3dUYdXPEWFB1FlAn6ac="
  },
  "133,122": {
    "SourceVersionHash": "1Y7b7F142apxQOh+8Cf4AoUWhAQ=",
    "VersionHash": "n9tKcnRK3dUYdXPEWFB1FlAn6ac="
  },
  "131,123": {
    "SourceVersionHash": "1Y7b7F142apxQOh+8Cf4AoUWhAQ=",
    "VersionHash": "n9tKcnRK3dUYdXPEWFB1FlAn6ac="
  },
  "131,121": {
    "SourceVersionHash": "1Y7b7F142apxQOh+8Cf4AoUWhAQ=",
    "VersionHash": "n9tKcnRK3dUYdXPEWFB1FlAn6ac="
  },
  "132,121": {
    "SourceVersionHash": "1Y7b7F142apxQOh+8Cf4AoUWhAQ=",
    "VersionHash": "n9tKcnRK3dUYdXPEWFB1FlAn6ac="
  },
  "130,121": {
    "SourceVersionHash": "1Y7b7F142apxQOh+8Cf4AoUWhAQ=",
    "VersionHash": "n9tKcnRK3dUYdXPEWFB1FlAn6ac="
  },
  "134,121": {
    "SourceVersionHash": "1Y7b7F142apxQOh+8Cf4AoUWhAQ=",
    "VersionHash": "n9tKcnRK3dUYdXPEWFB1FlAn6ac="
  },
  "135,123": {
    "SourceVersionHash": "1Y7b7F142apxQOh+8Cf4AoUWhAQ=",
    "VersionHash": "n9tKcnRK3dUYdXPEWFB1FlAn6ac="
  },
  "135,122": {
    "SourceVersionHash": "1Y7b7F142apxQOh+8Cf4AoUWhAQ=",
    "VersionHash": "n9tKcnRK3dUYdXPEWFB1FlAn6ac="
  },
  "135,124": {
    "SourceVersionHash": "1Y7b7F142apxQOh+8Cf4AoUWhAQ=",
    "VersionHash": "n9tKcnRK3dUYdXPEWFB1FlAn6ac="
  },
  "130,127": {
    "SourceVersionHash": "1Y7b7F142apxQOh+8Cf4AoUWhAQ=",
    "VersionHash": "n9tKcnRK3dUYdXPEWFB1FlAn6ac="
  },
  "134,127": {
    "SourceVersionHash": "1Y7b7F142apxQOh+8Cf4AoUWhAQ=",
    "VersionHash": "n9tKcnRK3dUYdXPEWFB1FlAn6ac="
  },
  "133,127": {
    "SourceVersionHash": "1Y7b7F142apxQOh+8Cf4AoUWhAQ=",
    "VersionHash": "n9tKcnRK3dUYdXPEWFB1FlAn6ac="
  },
  "131,122": {
    "SourceVersionHash": "1Y7b7F142apxQOh+8Cf4AoUWhAQ=",
    "VersionHash": "n9tKcnRK3dUYdXPEWFB1FlAn6ac="
  },
  "132,127": {
    "SourceVersionHash": "1Y7b7F142apxQOh+8Cf4AoUWhAQ=",
    "VersionHash": "n9tKcnRK3dUYdXPEWFB1FlAn6ac="
  },
  "134,120": {
    "SourceVersionHash": "1Y7b7F142apxQOh+8Cf4AoUWhAQ=",
    "VersionHash": "n9tKcnRK3dUYdXPEWFB1FlAn6ac="
  },
  "135,120": {
    "SourceVersionHash": "1Y7b7F142apxQOh+8Cf4AoUWhAQ=",
    "VersionHash": "n9tKcnRK3dUYdXPEWFB1FlAn6ac="
  },
  "131,127": {
    "SourceVersionHash": "1Y7b7F142apxQOh+8Cf4AoUWhAQ=",
    "VersionHash": "n9tKcnRK3dUYdXPEWFB1FlAn6ac="
  },
  "132,122": {
    "SourceVersionHash": "1Y7b7F142apxQOh+8Cf4AoUWhAQ=",
    "VersionHash": "n9tKcnRK3dUYdXPEWFB1FlAn6ac="
  },
  "135,126": {
    "SourceVersionHash": "1Y7b7F142apxQOh+8Cf4AoUWhAQ=",
    "VersionHash": "n9tKcnRK3dUYdXPEWFB1FlAn6ac="
  },
  "133,120": {
    "SourceVersionHash": "1Y7b7F142apxQOh+8Cf4AoUWhAQ=",
    "VersionHash": "n9tKcnRK3dUYdXPEWFB1FlAn6ac="
  },
  "132,120": {
    "SourceVersionHash": "1Y7b7F142apxQOh+8Cf4AoUWhAQ=",
    "VersionHash": "n9tKcnRK3dUYdXPEWFB1FlAn6ac="
  },
  "130,120": {
    "SourceVersionHash": "1Y7b7F142apxQOh+8Cf4AoUWhAQ=",
    "VersionHash": "n9tKcnRK3dUYdXPEWFB1FlAn6ac="
  },
  "130,123": {
    "SourceVersionHash": "1Y7b7F142apxQOh+8Cf4AoUWhAQ=",
    "VersionHash": "n9tKcnRK3dUYdXPEWFB1FlAn6ac="
  },
  "131,120": {
    "SourceVersionHash": "1Y7b7F142apxQOh+8Cf4AoUWhAQ=",
    "VersionHash": "n9tKcnRK3dUYdXPEWFB1FlAn6ac="
  },
  "134,123": {
    "SourceVersionHash": "1Y7b7F142apxQOh+8Cf4AoUWhAQ=",
    "VersionHash": "n9tKcnRK3dUYdXPEWFB1FlAn6ac="
  },
  "132,123": {
    "SourceVersionHash": "1Y7b7F142apxQOh+8Cf4AoUWhAQ=",
    "VersionHash": "n9tKcnRK3dUYdXPEWFB1FlAn6ac="
  },
  "130,122": {
    "SourceVersionHash": "1Y7b7F142apxQOh+8Cf4AoUWhAQ=",
    "VersionHash": "n9tKcnRK3dUYdXPEWFB1FlAn6ac="
  },
  "132,124": {
    "SourceVersionHash": "1Y7b7F142apxQOh+8Cf4AoUWhAQ=",
    "VersionHash": "n9tKcnRK3dUYdXPEWFB1FlAn6ac="
  },
  "130,124": {
    "SourceVersionHash": "1Y7b7F142apxQOh+8Cf4AoUWhAQ=",
    "VersionHash": "n9tKcnRK3dUYdXPEWFB1FlAn6ac="
  },
  "133,123": {
    "SourceVersionHash": "1Y7b7F142apxQOh+8Cf4AoUWhAQ=",
    "VersionHash": "n9tKcnRK3dUYdXPEWFB1FlAn6ac="
  },
  "130,125": {
    "SourceVersionHash": "1Y7b7F142apxQOh+8Cf4AoUWhAQ=",
    "VersionHash": "n9tKcnRK3dUYdXPEWFB1FlAn6ac="
  },
  "131,124": {
    "SourceVersionHash": "1Y7b7F142apxQOh+8Cf4AoUWhAQ=",
    "VersionHash": "n9tKcnRK3dUYdXPEWFB1FlAn6ac="
  },
  "135,127": {
    "SourceVersionHash": "1Y7b7F142apxQOh+8Cf4AoUWhAQ=",
    "VersionHash": "n9tKcnRK3dUYdXPEWFB1FlAn6ac="
  },
  "133,124": {
    "SourceVersionHash": "1Y7b7F142apxQOh+8Cf4AoUWhAQ=",
    "VersionHash": "n9tKcnRK3dUYdXPEWFB1FlAn6ac="
  },
  "133,125": {
    "SourceVersionHash": "1Y7b7F142apxQOh+8Cf4AoUWhAQ=",
    "VersionHash": "n9tKcnRK3dUYdXPEWFB1FlAn6ac="
  },
  "134,124": {
    "SourceVersionHash": "1Y7b7F142apxQOh+8Cf4AoUWhAQ=",
    "VersionHash": "n9tKcnRK3dUYdXPEWFB1FlAn6ac="
  },
  "132,125": {
    "SourceVersionHash": "1Y7b7F142apxQOh+8Cf4AoUWhAQ=",
    "VersionHash": "n9tKcnRK3dUYdXPEWFB1FlAn6ac="
  },
  "134,125": {
    "SourceVersionHash": "1Y7b7F142apxQOh+8Cf4AoUWhAQ=",
    "VersionHash": "n9tKcnRK3dUYdXPEWFB1FlAn6ac="
  },
  "132,126": {
    "SourceVersionHash": "1Y7b7F142apxQOh+8Cf4AoUWhAQ=",
    "VersionHash": "n9tKcnRK3dUYdXPEWFB1FlAn6ac="
  },
  "133,126": {
    "SourceVersionHash": "1Y7b7F142apxQOh+8Cf4AoUWhAQ=",
    "VersionHash": "n9tKcnRK3dUYdXPEWFB1FlAn6ac="
  },
  "134,126": {
    "SourceVersionHash": "1Y7b7F142apxQOh+8Cf4AoUWhAQ=",
    "VersionHash": "n9tKcnRK3dUYdXPEWFB1FlAn6ac="
  },
  "130,126": {
    "SourceVersionHash": "1Y7b7F142apxQOh+8Cf4AoUWhAQ=",
    "VersionHash": "n9tKcnRK3dUYdXPEWFB1FlAn6ac="
  },
  "134,122": {
    "SourceVersionHash": "1Y7b7F142apxQOh+8Cf4AoUWhAQ=",
    "VersionHash": "n9tKcnRK3dUYdXPEWFB1FlAn6ac="
  },
  "131,126": {
    "SourceVersionHash": "1Y7b7F142apxQOh+8Cf4AoUWhAQ=",
    "VersionHash": "n9tKcnRK3dUYdXPEWFB1FlAn6ac="
  },
  "131,125": {
    "SourceVersionHash": "1Y7b7F142apxQOh+8Cf4AoUWhAQ=",
    "VersionHash": "n9tKcnRK3dUYdXPEWFB1FlAn6ac="
  },
  "135,125": {
    "SourceVersionHash": "1Y7b7F142apxQOh+8Cf4AoUWhAQ=",
    "VersionHash": "n9tKcnRK3dUYdXPEWFB1FlAn6ac="
  }
}