{
  "15,44": {
    "SourceVersionHash": "tSVOy32vtf/UYOgo6sKGcbvxvF0=",
    "VersionHash": "IxwoemIIDnCaba8l3qk6ut6VDCU="
  },
  "17,47": {
    "SourceVersionHash": "kg+aPmHaHLxm6HP5iy9y790PbZs=",
    "VersionHash": "IxwoemIIDnCaba8l3qk6ut6VDCU="
  },
  "17,48": {
    "SourceVersionHash": "kg+aPmHaHLxm6HP5iy9y790PbZs=",
    "VersionHash": "IxwoemIIDnCaba8l3qk6ut6VDCU="
  },
  "18,48": {
    "SourceVersionHash": "kg+aPmHaHLxm6HP5iy9y790PbZs=",
    "VersionHash": "IxwoemIIDnCaba8l3qk6ut6VDCU="
  },
  "18,47": {
    "SourceVersionHash": "kg+aPmHaHLxm6HP5iy9y790PbZs=",
    "VersionHash": "IxwoemIIDnCaba8l3qk6ut6VDCU="
  },
  "16,41": {
    "SourceVersionHash": "kg+aPmHaHLxm6HP5iy9y790PbZs=",
    "VersionHash": "IxwoemIIDnCaba8l3qk6ut6VDCU="
  },
  "15,41": {
    "SourceVersionHash": "tSVOy32vtf/UYOgo6sKGcbvxvF0=",
    "VersionHash": "IxwoemIIDnCaba8l3qk6ut6VDCU="
  },
  "17,41": {
    "SourceVersionHash": "kg+aPmHaHLxm6HP5iy9y790PbZs=",
    "VersionHash": "IxwoemIIDnCaba8l3qk6ut6VDCU="
  },
  "19,47": {
    "SourceVersionHash": "kg+aPmHaHLxm6HP5iy9y790PbZs=",
    "VersionHash": "IxwoemIIDnCaba8l3qk6ut6VDCU="
  },
  "19,41": {
    "SourceVersionHash": "kg+aPmHaHLxm6HP5iy9y790PbZs=",
    "VersionHash": "IxwoemIIDnCaba8l3qk6ut6VDCU="
  },
  "15,42": {
    "SourceVersionHash": "tSVOy32vtf/UYOgo6sKGcbvxvF0=",
    "VersionHash": "IxwoemIIDnCaba8l3qk6ut6VDCU="
  },
  "16,42": {
    "SourceVersionHash": "kg+aPmHaHLxm6HP5iy9y790PbZs=",
    "VersionHash": "IxwoemIIDnCaba8l3qk6ut6VDCU="
  },
  "19,48": {
    "SourceVersionHash": "kg+aPmHaHLxm6HP5iy9y790PbZs=",
    "VersionHash": "IxwoemIIDnCaba8l3qk6ut6VDCU="
  },
  "18,41": {
    "SourceVersionHash": "kg+aPmHaHLxm6HP5iy9y790PbZs=",
    "VersionHash": "IxwoemIIDnCaba8l3qk6ut6VDCU="
  },
  "18,42": {
    "SourceVersionHash": "kg+aPmHaHLxm6HP5iy9y790PbZs=",
    "VersionHash": "IxwoemIIDnCaba8l3qk6ut6VDCU="
  },
  "16,44": {
    "SourceVersionHash": "kg+aPmHaHLxm6HP5iy9y790PbZs=",
    "VersionHash": "IxwoemIIDnCaba8l3qk6ut6VDCU="
  },
  "15,47": {
    "SourceVersionHash": "tSVOy32vtf/UYOgo6sKGcbvxvF0=",
    "VersionHash": "IxwoemIIDnCaba8l3qk6ut6VDCU="
  },
  "16,48": {
    "SourceVersionHash": "kg+aPmHaHLxm6HP5iy9y790PbZs=",
    "VersionHash": "IxwoemIIDnCaba8l3qk6ut6VDCU="
  },
  "15,43": {
    "SourceVersionHash": "tSVOy32vtf/UYOgo6sKGcbvxvF0=",
    "VersionHash": "IxwoemIIDnCaba8l3qk6ut6VDCU="
  },
  "16,47": {
    "SourceVersionHash": "kg+aPmHaHLxm6HP5iy9y790PbZs=",
    "VersionHash": "IxwoemIIDnCaba8l3qk6ut6VDCU="
  },
  "16,43": {
    "SourceVersionHash": "kg+aPmHaHLxm6HP5iy9y790PbZs=",
    "VersionHash": "IxwoemIIDnCaba8l3qk6ut6VDCU="
  },
  "17,40": {
    "SourceVersionHash": "kg+aPmHaHLxm6HP5iy9y790PbZs=",
    "VersionHash": "gMB4SMV/HkOV2/RyMIkzTJwCzTo="
  },
  "16,45": {
    "SourceVersionHash": "kg+aPmHaHLxm6HP5iy9y790PbZs=",
    "VersionHash": "gMB4SMV/HkOV2/RyMIkzTJwCzTo="
  },
  "19,43": {
    "SourceVersionHash": "kg+aPmHaHLxm6HP5iy9y790PbZs=",
    "VersionHash": "gMB4SMV/HkOV2/RyMIkzTJwCzTo="
  },
  "15,48": {
    "SourceVersionHash": "1Y7b7F142apxQOh+8Cf4AoUWhAQ=",
    "VersionHash": "gMB4SMV/HkOV2/RyMIkzTJwCzTo="
  },
  "18,40": {
    "SourceVersionHash": "kg+aPmHaHLxm6HP5iy9y790PbZs=",
    "VersionHash": "gMB4SMV/HkOV2/RyMIkzTJwCzTo="
  },
  "19,40": {
    "SourceVersionHash": "kg+aPmHaHLxm6HP5iy9y790PbZs=",
    "VersionHash": "gMB4SMV/HkOV2/RyMIkzTJwCzTo="
  },
  "15,40": {
    "SourceVersionHash": "tSVOy32vtf/UYOgo6sKGcbvxvF0=",
    "VersionHash": "gMB4SMV/HkOV2/RyMIkzTJwCzTo="
  },
  "16,40": {
    "SourceVersionHash": "kg+aPmHaHLxm6HP5iy9y790PbZs=",
    "VersionHash": "gMB4SMV/HkOV2/RyMIkzTJwCzTo="
  },
  "15,46": {
    "SourceVersionHash": "tSVOy32vtf/UYOgo6sKGcbvxvF0=",
    "VersionHash": "gMB4SMV/HkOV2/RyMIkzTJwCzTo="
  },
  "18,43": {
    "SourceVersionHash": "kg+aPmHaHLxm6HP5iy9y790PbZs=",
    "VersionHash": "gMB4SMV/HkOV2/RyMIkzTJwCzTo="
  },
  "16,46": {
    "SourceVersionHash": "kg+aPmHaHLxm6HP5iy9y790PbZs=",
    "VersionHash": "gMB4SMV/HkOV2/RyMIkzTJwCzTo="
  },
  "18,44": {
    "SourceVersionHash": "kg+aPmHaHLxm6HP5iy9y790PbZs=",
    "VersionHash": "gMB4SMV/HkOV2/RyMIkzTJwCzTo="
  },
  "19,42": {
    "SourceVersionHash": "kg+aPmHaHLxm6HP5iy9y790PbZs=",
    "VersionHash": "gMB4SMV/HkOV2/RyMIkzTJwCzTo="
  },
  "17,44": {
    "SourceVersionHash": "kg+aPmHaHLxm6HP5iy9y790PbZs=",
    "VersionHash": "gMB4SMV/HkOV2/RyMIkzTJwCzTo="
  },
  "17,45": {
    "SourceVersionHash": "kg+aPmHaHLxm6HP5iy9y790PbZs=",
    "VersionHash": "gMB4SMV/HkOV2/RyMIkzTJwCzTo="
  },
  "18,45": {
    "SourceVersionHash": "kg+aPmHaHLxm6HP5iy9y790PbZs=",
    "VersionHash": "gMB4SMV/HkOV2/RyMIkzTJwCzTo="
  },
  "19,45": {
    "SourceVersionHash": "kg+aPmHaHLxm6HP5iy9y790PbZs=",
    "VersionHash": "gMB4SMV/HkOV2/RyMIkzTJwCzTo="
  },
  "17,42": {
    "SourceVersionHash": "kg+aPmHaHLxm6HP5iy9y790PbZs=",
    "VersionHash": "gMB4SMV/HkOV2/RyMIkzTJwCzTo="
  },
  "17,43": {
    "SourceVersionHash": "kg+aPmHaHLxm6HP5iy9y790PbZs=",
    "VersionHash": "gMB4SMV/HkOV2/RyMIkzTJwCzTo="
  },
  "17,46": {
    "SourceVersionHash": "kg+aPmHaHLxm6HP5iy9y790PbZs=",
    "VersionHash": "gMB4SMV/HkOV2/RyMIkzTJwCzTo="
  },
  "18,46": {
    "SourceVersionHash": "kg+aPmHaHLxm6HP5iy9y790PbZs=",
    "VersionHash": "gMB4SMV/HkOV2/RyMIkzTJwCzTo="
  },
  "19,46": {
    "SourceVersionHash": "kg+aPmHaHLxm6HP5iy9y790PbZs=",
    "VersionHash": "gMB4SMV/HkOV2/RyMIkzTJwCzTo="
  },
  "15,45": {
    "SourceVersionHash": "tSVOy32vtf/UYOgo6sKGcbvxvF0=",
    "VersionHash": "IxwoemIIDnCaba8l3qk6ut6VDCU="
  },
  "19,44": {
    "SourceVersionHash": "kg+aPmHaHLxm6HP5iy9y790PbZs=",
    "VersionHash": "gMB4SMV/HkOV2/RyMIkzTJwCzTo="
  },
  "13,40": {
    "SourceVersionHash": "tSVOy32vtf/UYOgo6sKGcbvxvF0=",
    "VersionHash": "Q2ARWqvod1mhF+WdKxAjr59vIhM="
  },
  "10,47": {
    "SourceVersionHash": "tSVOy32vtf/UYOgo6sKGcbvxvF0=",
    "VersionHash": "rbIlb8dgEs27WD0SUD97o/roOns="
  },
  "12,44": {
    "SourceVersionHash": "tSVOy32vtf/UYOgo6sKGcbvxvF0=",
    "VersionHash": "Q2ARWqvod1mhF+WdKxAjr59vIhM="
  },
  "14,41": {
    "SourceVersionHash": "tSVOy32vtf/UYOgo6sKGcbvxvF0=",
    "VersionHash": "rbIlb8dgEs27WD0SUD97o/roOns="
  },
  "11,41": {
    "SourceVersionHash": "tSVOy32vtf/UYOgo6sKGcbvxvF0=",
    "VersionHash": "rbIlb8dgEs27WD0SUD97o/roOns="
  },
  "12,41": {
    "SourceVersionHash": "tSVOy32vtf/UYOgo6sKGcbvxvF0=",
    "VersionHash": "rbIlb8dgEs27WD0SUD97o/roOns="
  },
  "11,42": {
    "SourceVersionHash": "tSVOy32vtf/UYOgo6sKGcbvxvF0=",
    "VersionHash": "rbIlb8dgEs27WD0SUD97o/roOns="
  },
  "10,42": {
    "SourceVersionHash": "tSVOy32vtf/UYOgo6sKGcbvxvF0=",
    "VersionHash": "rbIlb8dgEs27WD0SUD97o/roOns="
  },
  "11,47": {
    "SourceVersionHash": "tSVOy32vtf/UYOgo6sKGcbvxvF0=",
    "VersionHash": "rbIlb8dgEs27WD0SUD97o/roOns="
  },
  "12,47": {
    "SourceVersionHash": "tSVOy32vtf/UYOgo6sKGcbvxvF0=",
    "VersionHash": "rbIlb8dgEs27WD0SUD97o/roOns="
  },
  "10,41": {
    "SourceVersionHash": "tSVOy32vtf/UYOgo6sKGcbvxvF0=",
    "VersionHash": "rbIlb8dgEs27WD0SUD97o/roOns="
  },
  "14,42": {
    "SourceVersionHash": "tSVOy32vtf/UYOgo6sKGcbvxvF0=",
    "VersionHash": "rbIlb8dgEs27WD0SUD97o/roOns="
  },
  "10,43": {
    "SourceVersionHash": "tSVOy32vtf/UYOgo6sKGcbvxvF0=",
    "VersionHash": "rbIlb8dgEs27WD0SUD97o/roOns="
  },
  "10,40": {
    "SourceVersionHash": "tSVOy32vtf/UYOgo6sKGcbvxvF0=",
    "VersionHash": "rbIlb8dgEs27WD0SUD97o/roOns="
  },
  "14,47": {
    "SourceVersionHash": "tSVOy32vtf/UYOgo6sKGcbvxvF0=",
    "VersionHash": "rbIlb8dgEs27WD0SUD97o/roOns="
  },
  "13,47": {
    "SourceVersionHash": "tSVOy32vtf/UYOgo6sKGcbvxvF0=",
    "VersionHash": "rbIlb8dgEs27WD0SUD97o/roOns="
  },
  "13,41": {
    "SourceVersionHash": "tSVOy32vtf/UYOgo6sKGcbvxvF0=",
    "VersionHash": "rbIlb8dgEs27WD0SUD97o/roOns="
  },
  "13,43": {
    "SourceVersionHash": "tSVOy32vtf/UYOgo6sKGcbvxvF0=",
    "VersionHash": "rbIlb8dgEs27WD0SUD97o/roOns="
  },
  "14,43": {
    "SourceVersionHash": "tSVOy32vtf/UYOgo6sKGcbvxvF0=",
    "VersionHash": "rbIlb8dgEs27WD0SUD97o/roOns="
  },
  "11,43": {
    "SourceVersionHash": "tSVOy32vtf/UYOgo6sKGcbvxvF0=",
    "VersionHash": "rbIlb8dgEs27WD0SUD97o/roOns="
  },
  "11,40": {
    "SourceVersionHash": "tSVOy32vtf/UYOgo6sKGcbvxvF0=",
    "VersionHash": "Q2ARWqvod1mhF+WdKxAjr59vIhM="
  },
  "12,40": {
    "SourceVersionHash": "tSVOy32vtf/UYOgo6sKGcbvxvF0=",
    "VersionHash": "Q2ARWqvod1mhF+WdKxAjr59vIhM="
  },
  "14,48": {
    "SourceVersionHash": "1Y7b7F142apxQOh+8Cf4AoUWhAQ=",
    "VersionHash": "Q2ARWqvod1mhF+WdKxAjr59vIhM="
  },
  "14,40": {
    "SourceVersionHash": "tSVOy32vtf/UYOgo6sKGcbvxvF0=",
    "VersionHash": "Q2ARWqvod1mhF+WdKxAjr59vIhM="
  },
  "12,43": {
    "SourceVersionHash": "tSVOy32vtf/UYOgo6sKGcbvxvF0=",
    "VersionHash": "Q2ARWqvod1mhF+WdKxAjr59vIhM="
  },
  "11,48": {
    "SourceVersionHash": "1Y7b7F142apxQOh+8Cf4AoUWhAQ=",
    "VersionHash": "Q2ARWqvod1mhF+WdKxAjr59vIhM="
  },
  "10,48": {
    "SourceVersionHash": "1Y7b7F142apxQOh+8Cf4AoUWhAQ=",
    "VersionHash": "Q2ARWqvod1mhF+WdKxAjr59vIhM="
  },
  "12,48": {
    "SourceVersionHash": "1Y7b7F142apxQOh+8Cf4AoUWhAQ=",
    "VersionHash": "Q2ARWqvod1mhF+WdKxAjr59vIhM="
  },
  "13,48": {
    "SourceVersionHash": "1Y7b7F142apxQOh+8Cf4AoUWhAQ=",
    "VersionHash": "Q2ARWqvod1mhF+WdKxAjr59vIhM="
  },
  "10,44": {
    "SourceVersionHash": "tSVOy32vtf/UYOgo6sKGcbvxvF0=",
    "VersionHash": "Q2ARWqvod1mhF+WdKxAjr59vIhM="
  },
  "11,45": {
    "SourceVersionHash": "tSVOy32vtf/UYOgo6sKGcbvxvF0=",
    "VersionHash": "Q2ARWqvod1mhF+WdKxAjr59vIhM="
  },
  "10,45": {
    "SourceVersionHash": "tSVOy32vtf/UYOgo6sKGcbvxvF0=",
    "VersionHash": "Q2ARWqvod1mhF+WdKxAjr59vIhM="
  },
  "12,45": {
    "SourceVersionHash": "tSVOy32vtf/UYOgo6sKGcbvxvF0=",
    "VersionHash": "Q2ARWqvod1mhF+WdKxAjr59vIhM="
  },
  "11,44": {
    "SourceVersionHash": "tSVOy32vtf/UYOgo6sKGcbvxvF0=",
    "VersionHash": "Q2ARWqvod1mhF+WdKxAjr59vIhM="
  },
  "14,45": {
    "SourceVersionHash": "tSVOy32vtf/UYOgo6sKGcbvxvF0=",
    "VersionHash": "Q2ARWqvod1mhF+WdKxAjr59vIhM="
  },
  "13,44": {
    "SourceVersionHash": "tSVOy32vtf/UYOgo6sKGcbvxvF0=",
    "VersionHash": "Q2ARWqvod1mhF+WdKxAjr59vIhM="
  },
  "14,44": {
    "SourceVersionHash": "tSVOy32vtf/UYOgo6sKGcbvxvF0=",
    "VersionHash": "Q2ARWqvod1mhF+WdKxAjr59vIhM="
  },
  "10,46": {
    "SourceVersionHash": "tSVOy32vtf/UYOgo6sKGcbvxvF0=",
    "VersionHash": "Q2ARWqvod1mhF+WdKxAjr59vIhM="
  },
  "13,46": {
    "SourceVersionHash": "tSVOy32vtf/UYOgo6sKGcbvxvF0=",
    "VersionHash": "Q2ARWqvod1mhF+WdKxAjr59vIhM="
  },
  "14,46": {
    "SourceVersionHash": "tSVOy32vtf/UYOgo6sKGcbvxvF0=",
    "VersionHash": "Q2ARWqvod1mhF+WdKxAjr59vIhM="
  },
  "12,46": {
    "SourceVersionHash": "tSVOy32vtf/UYOgo6sKGcbvxvF0=",
    "VersionHash": "Q2ARWqvod1mhF+WdKxAjr59vIhM="
  },
  "13,45": {
    "SourceVersionHash": "tSVOy32vtf/UYOgo6sKGcbvxvF0=",
    "VersionHash": "Q2ARWqvod1mhF+WdKxAjr59vIhM="
  },
  "11,46": {
    "SourceVersionHash": "tSVOy32vtf/UYOgo6sKGcbvxvF0=",
    "VersionHash": "Q2ARWqvod1mhF+WdKxAjr59vIhM="
  },
  "13,42": {
    "SourceVersionHash": "tSVOy32vtf/UYOgo6sKGcbvxvF0=",
    "VersionHash": "Q2ARWqvod1mhF+WdKxAjr59vIhM="
  },
  "12,42": {
    "SourceVersionHash": "tSVOy32vtf/UYOgo6sKGcbvxvF0=",
    "VersionHash": "Q2ARWqvod1mhF+WdKxAjr59vIhM="
  },
  "17,49": {
    "SourceVersionHash": "kg+aPmHaHLxm6HP5iy9y790PbZs=",
    "VersionHash": "8a6HU8vsZEf+NuQl7WDcOU0lHdY="
  },
  "18,49": {
    "SourceVersionHash": "kg+aPmHaHLxm6HP5iy9y790PbZs=",
    "VersionHash": "8a6HU8vsZEf+NuQl7WDcOU0lHdY="
  },
  "19,49": {
    "SourceVersionHash": "kg+aPmHaHLxm6HP5iy9y790PbZs=",
    "VersionHash": "8a6HU8vsZEf+NuQl7WDcOU0lHdY="
  },
  "15,49": {
    "SourceVersionHash": "1Y7b7F142apxQOh+8Cf4AoUWhAQ=",
    "VersionHash": "MBATrisTdstKuYAE+YpNYFdyYR0="
  },
  "16,49": {
    "SourceVersionHash": "kg+aPmHaHLxm6HP5iy9y790PbZs=",
    "VersionHash": "MBATrisTdstKuYAE+YpNYFdyYR0="
  }
}