{
  "71,91": {
    "SourceVersionHash": "1Y7b7F142apxQOh+8Cf4AoUWhAQ=",
    "VersionHash": "OnwLIi1RK46KdJDDXt9cxhSq62s="
  },
  "71,92": {
    "SourceVersionHash": "1Y7b7F142apxQOh+8Cf4AoUWhAQ=",
    "VersionHash": "OnwLIi1RK46KdJDDXt9cxhSq62s="
  },
  "71,94": {
    "SourceVersionHash": "1Y7b7F142apxQOh+8Cf4AoUWhAQ=",
    "VersionHash": "OnwLIi1RK46KdJDDXt9cxhSq62s="
  },
  "71,90": {
    "SourceVersionHash": "1Y7b7F142apxQOh+8Cf4AoUWhAQ=",
    "VersionHash": "OnwLIi1RK46KdJDDXt9cxhSq62s="
  },
  "71,93": {
    "SourceVersionHash": "1Y7b7F142apxQOh+8Cf4AoUWhAQ=",
    "VersionHash": "OnwLIi1RK46KdJDDXt9cxhSq62s="
  },
  "70,95": {
    "SourceVersionHash": "1Y7b7F142apxQOh+8Cf4AoUWhAQ=",
    "VersionHash": "OnwLIi1RK46KdJDDXt9cxhSq62s="
  },
  "71,95": {
    "SourceVersionHash": "1Y7b7F142apxQOh+8Cf4AoUWhAQ=",
    "VersionHash": "OnwLIi1RK46KdJDDXt9cxhSq62s="
  },
  "70,91": {
    "SourceVersionHash": "1Y7b7F142apxQOh+8Cf4AoUWhAQ=",
    "VersionHash": "n9tKcnRK3dUYdXPEWFB1FlAn6ac="
  },
  "70,92": {
    "SourceVersionHash": "1Y7b7F142apxQOh+8Cf4AoUWhAQ=",
    "VersionHash": "n9tKcnRK3dUYdXPEWFB1FlAn6ac="
  },
  "70,93": {
    "SourceVersionHash": "1Y7b7F142apxQOh+8Cf4AoUWhAQ=",
    "VersionHash": "n9tKcnRK3dUYdXPEWFB1FlAn6ac="
  },
  "70,94": {
    "SourceVersionHash": "1Y7b7F142apxQOh+8Cf4AoUWhAQ=",
    "VersionHash": "n9tKcnRK3dUYdXPEWFB1FlAn6ac="
  },
  "70,90": {
    "SourceVersionHash": "1Y7b7F142apxQOh+8Cf4AoUWhAQ=",
    "VersionHash": "n9tKcnRK3dUYdXPEWFB1FlAn6ac="
  }
}