{
  "-136,23": {
    "SourceVersionHash": "1Y7b7F142apxQOh+8Cf4AoUWhAQ=",
    "VersionHash": "m03feV7fdCEgJDDDAPT6lxG2qW0="
  },
  "-132,23": {
    "SourceVersionHash": "1Y7b7F142apxQOh+8Cf4AoUWhAQ=",
    "VersionHash": "m03feV7fdCEgJDDDAPT6lxG2qW0="
  },
  "-136,22": {
    "SourceVersionHash": "1Y7b7F142apxQOh+8Cf4AoUWhAQ=",
    "VersionHash": "m03feV7fdCEgJDDDAPT6lxG2qW0="
  },
  "-135,23": {
    "SourceVersionHash": "1Y7b7F142apxQOh+8Cf4AoUWhAQ=",
    "VersionHash": "m03feV7fdCEgJDDDAPT6lxG2qW0="
  },
  "-131,23": {
    "SourceVersionHash": "1Y7b7F142apxQOh+8Cf4AoUWhAQ=",
    "VersionHash": "m03feV7fdCEgJDDDAPT6lxG2qW0="
  },
  "-136,21": {
    "SourceVersionHash": "1Y7b7F142apxQOh+8Cf4AoUWhAQ=",
    "VersionHash": "m03feV7fdCEgJDDDAPT6lxG2qW0="
  },
  "-133,23": {
    "SourceVersionHash": "1Y7b7F142apxQOh+8Cf4AoUWhAQ=",
    "VersionHash": "m03feV7fdCEgJDDDAPT6lxG2qW0="
  },
  "-134,23": {
    "SourceVersionHash": "1Y7b7F142apxQOh+8Cf4AoUWhAQ=",
    "VersionHash": "m03feV7fdCEgJDDDAPT6lxG2qW0="
  },
  "-134,20": {
    "SourceVersionHash": "1Y7b7F142apxQOh+8Cf4AoUWhAQ=",
    "VersionHash": "m03feV7fdCEgJDDDAPT6lxG2qW0="
  },
  "-136,20": {
    "SourceVersionHash": "1Y7b7F142apxQOh+8Cf4AoUWhAQ=",
    "VersionHash": "m03feV7fdCEgJDDDAPT6lxG2qW0="
  },
  "-131,20": {
    "SourceVersionHash": "1Y7b7F142apxQOh+8Cf4AoUWhAQ=",
    "VersionHash": "m03feV7fdCEgJDDDAPT6lxG2qW0="
  },
  "-132,20": {
    "SourceVersionHash": "1Y7b7F142apxQOh+8Cf4AoUWhAQ=",
    "VersionHash": "m03feV7fdCEgJDDDAPT6lxG2qW0="
  },
  "-133,20": {
    "SourceVersionHash": "1Y7b7F142apxQOh+8Cf4AoUWhAQ=",
    "VersionHash": "m03feV7fdCEgJDDDAPT6lxG2qW0="
  },
  "-134,21": {
    "SourceVersionHash": "1Y7b7F142apxQOh+8Cf4AoUWhAQ=",
    "VersionHash": "m03feV7fdCEgJDDDAPT6lxG2qW0="
  },
  "-133,21": {
    "SourceVersionHash": "1Y7b7F142apxQOh+8Cf4AoUWhAQ=",
    "VersionHash": "m03feV7fdCEgJDDDAPT6lxG2qW0="
  },
  "-132,21": {
    "SourceVersionHash": "1Y7b7F142apxQOh+8Cf4AoUWhAQ=",
    "VersionHash": "m03feV7fdCEgJDDDAPT6lxG2qW0="
  },
  "-135,21": {
    "SourceVersionHash": "1Y7b7F142apxQOh+8Cf4AoUWhAQ=",
    "VersionHash": "m03feV7fdCEgJDDDAPT6lxG2qW0="
  },
  "-131,21": {
    "SourceVersionHash": "1Y7b7F142apxQOh+8Cf4AoUWhAQ=",
    "VersionHash": "m03feV7fdCEgJDDDAPT6lxG2qW0="
  },
  "-134,22": {
    "SourceVersionHash": "1Y7b7F142apxQOh+8Cf4AoUWhAQ=",
    "VersionHash": "m03feV7fdCEgJDDDAPT6lxG2qW0="
  },
  "-133,22": {
    "SourceVersionHash": "1Y7b7F142apxQOh+8Cf4AoUWhAQ=",
    "VersionHash": "m03feV7fdCEgJDDDAPT6lxG2qW0="
  },
  "-132,22": {
    "SourceVersionHash": "1Y7b7F142apxQOh+8Cf4AoUWhAQ=",
    "VersionHash": "m03feV7fdCEgJDDDAPT6lxG2qW0="
  },
  "-135,22": {
    "SourceVersionHash": "1Y7b7F142apxQOh+8Cf4AoUWhAQ=",
    "VersionHash": "m03feV7fdCEgJDDDAPT6lxG2qW0="
  },
  "-131,22": {
    "SourceVersionHash": "1Y7b7F142apxQOh+8Cf4AoUWhAQ=",
    "VersionHash": "m03feV7fdCEgJDDDAPT6lxG2qW0="
  },
  "-135,20": {
    "SourceVersionHash": "1Y7b7F142apxQOh+8Cf4AoUWhAQ=",
    "VersionHash": "m03feV7fdCEgJDDDAPT6lxG2qW0="
  }
}