{
  "11,10": {
    "SourceVersionHash": "F9ATle/t34kEqqs0pvnfN0B3G0M=",
    "VersionHash": "gVxTHtIDVsGrakQHZcd4XiqxujI="
  },
  "13,10": {
    "SourceVersionHash": "K9Jp5IY6IBEUn8KrmlT+eDHx7Co=",
    "VersionHash": "gVxTHtIDVsGrakQHZcd4XiqxujI="
  },
  "18,10": {
    "SourceVersionHash": "BlrloIIvfnafgH4edGXa088w8zE=",
    "VersionHash": "gVxTHtIDVsGrakQHZcd4XiqxujI="
  },
  "16,11": {
    "SourceVersionHash": "K9Jp5IY6IBEUn8KrmlT+eDHx7Co=",
    "VersionHash": "gVxTHtIDVsGrakQHZcd4XiqxujI="
  },
  "11,13": {
    "SourceVersionHash": "LwuTV4a7K7O0nyCw+nHoYZItft0=",
    "VersionHash": "kOorCY6ACAyyy7lrgNEnYX95aio="
  },
  "14,13": {
    "SourceVersionHash": "spcVJLYmq3O1MqdJ1aFUucZovo4=",
    "VersionHash": "kOorCY6ACAyyy7lrgNEnYX95aio="
  },
  "16,13": {
    "SourceVersionHash": "g+72WRtE61CRdJcD5vX2L+NfAy0=",
    "VersionHash": "kOorCY6ACAyyy7lrgNEnYX95aio="
  },
  "17,13": {
    "SourceVersionHash": "NfdG2koBI+CwP49TMnNHWTWrPY0=",
    "VersionHash": "kOorCY6ACAyyy7lrgNEnYX95aio="
  },
  "13,15": {
    "SourceVersionHash": "JpUd0U6dH8J6bYHN+/O4QNPeEIQ=",
    "VersionHash": "elu97Btl5U2COAExzfbijLgLtPk="
  },
  "16,15": {
    "SourceVersionHash": "w04IS9lxy/gPzbczK+uWdn6q/sk=",
    "VersionHash": "elu97Btl5U2COAExzfbijLgLtPk="
  },
  "10,16": {
    "SourceVersionHash": "BlrloIIvfnafgH4edGXa088w8zE=",
    "VersionHash": "elu97Btl5U2COAExzfbijLgLtPk="
  },
  "18,16": {
    "SourceVersionHash": "h0iYxygeH1U1MV6W5FzDkVjWpf8=",
    "VersionHash": "elu97Btl5U2COAExzfbijLgLtPk="
  },
  "17,17": {
    "SourceVersionHash": "LtyFjcaSCX2TjnaqzxEU0IWNMDM=",
    "VersionHash": "elu97Btl5U2COAExzfbijLgLtPk="
  },
  "11,18": {
    "SourceVersionHash": "F9ATle/t34kEqqs0pvnfN0B3G0M=",
    "VersionHash": "elu97Btl5U2COAExzfbijLgLtPk="
  },
  "14,18": {
    "SourceVersionHash": "2+xenssoNgeOm3DaZMHpHNJMBmk=",
    "VersionHash": "71d79vdiSlVaIfrE3HoKjTK2zus="
  },
  "15,18": {
    "SourceVersionHash": "fN3uZjAf7tMj9SLl7pJe4sVUIh0=",
    "VersionHash": "71d79vdiSlVaIfrE3HoKjTK2zus="
  }
}