{
  "12,-119": {
    "SourceVersionHash": "XE2vRkX6NFCGRuMC4J/wFaBQ9nA=",
    "VersionHash": "lx4Pm0Wdm7JE9RVIkggHMmg3fbQ="
  },
  "13,-120": {
    "SourceVersionHash": "XE2vRkX6NFCGRuMC4J/wFaBQ9nA=",
    "VersionHash": "lx4Pm0Wdm7JE9RVIkggHMmg3fbQ="
  },
  "13,-117": {
    "SourceVersionHash": "XE2vRkX6NFCGRuMC4J/wFaBQ9nA=",
    "VersionHash": "lx4Pm0Wdm7JE9RVIkggHMmg3fbQ="
  },
  "14,-117": {
    "SourceVersionHash": "XE2vRkX6NFCGRuMC4J/wFaBQ9nA=",
    "VersionHash": "lx4Pm0Wdm7JE9RVIkggHMmg3fbQ="
  },
  "15,-120": {
    "SourceVersionHash": "XE2vRkX6NFCGRuMC4J/wFaBQ9nA=",
    "VersionHash": "lx4Pm0Wdm7JE9RVIkggHMmg3fbQ="
  },
  "14,-120": {
    "SourceVersionHash": "XE2vRkX6NFCGRuMC4J/wFaBQ9nA=",
    "VersionHash": "lx4Pm0Wdm7JE9RVIkggHMmg3fbQ="
  },
  "15,-117": {
    "SourceVersionHash": "XE2vRkX6NFCGRuMC4J/wFaBQ9nA=",
    "VersionHash": "lx4Pm0Wdm7JE9RVIkggHMmg3fbQ="
  },
  "15,-118": {
    "SourceVersionHash": "XE2vRkX6NFCGRuMC4J/wFaBQ9nA=",
    "VersionHash": "lx4Pm0Wdm7JE9RVIkggHMmg3fbQ="
  },
  "14,-118": {
    "SourceVersionHash": "XE2vRkX6NFCGRuMC4J/wFaBQ9nA=",
    "VersionHash": "lx4Pm0Wdm7JE9RVIkggHMmg3fbQ="
  },
  "14,-119": {
    "SourceVersionHash": "XE2vRkX6NFCGRuMC4J/wFaBQ9nA=",
    "VersionHash": "lx4Pm0Wdm7JE9RVIkggHMmg3fbQ="
  },
  "12,-118": {
    "SourceVersionHash": "XE2vRkX6NFCGRuMC4J/wFaBQ9nA=",
    "VersionHash": "lx4Pm0Wdm7JE9RVIkggHMmg3fbQ="
  },
  "13,-119": {
    "SourceVersionHash": "XE2vRkX6NFCGRuMC4J/wFaBQ9nA=",
    "VersionHash": "lx4Pm0Wdm7JE9RVIkggHMmg3fbQ="
  },
  "15,-119": {
    "SourceVersionHash": "XE2vRkX6NFCGRuMC4J/wFaBQ9nA=",
    "VersionHash": "lx4Pm0Wdm7JE9RVIkggHMmg3fbQ="
  },
  "13,-118": {
    "SourceVersionHash": "XE2vRkX6NFCGRuMC4J/wFaBQ9nA=",
    "VersionHash": "lx4Pm0Wdm7JE9RVIkggHMmg3fbQ="
  },
  "12,-120": {
    "SourceVersionHash": "XE2vRkX6NFCGRuMC4J/wFaBQ9nA=",
    "VersionHash": "CeXGnIlbzKkMY55Ym39xDvxC4cU="
  },
  "12,-117": {
    "SourceVersionHash": "XE2vRkX6NFCGRuMC4J/wFaBQ9nA=",
    "VersionHash": "vEkqN2+TMS0ozvlfEQM1seO1bgQ="
  }
}