{
  "-34,-27": {
    "SourceVersionHash": "1Y7b7F142apxQOh+8Cf4AoUWhAQ=",
    "VersionHash": "/jlSV4RFu5Yy7lzJiQdC65kPcd8="
  },
  "-35,-26": {
    "SourceVersionHash": "1Y7b7F142apxQOh+8Cf4AoUWhAQ=",
    "VersionHash": "/jlSV4RFu5Yy7lzJiQdC65kPcd8="
  },
  "-34,-26": {
    "SourceVersionHash": "1Y7b7F142apxQOh+8Cf4AoUWhAQ=",
    "VersionHash": "/jlSV4RFu5Yy7lzJiQdC65kPcd8="
  },
  "-35,-27": {
    "SourceVersionHash": "1Y7b7F142apxQOh+8Cf4AoUWhAQ=",
    "VersionHash": "fySDkHYy8/5IClNmEcPubrE3KEs="
  },
  "-36,-26": {
    "SourceVersionHash": "1Y7b7F142apxQOh+8Cf4AoUWhAQ=",
    "VersionHash": "fySDkHYy8/5IClNmEcPubrE3KEs="
  },
  "-36,-27": {
    "SourceVersionHash": "1Y7b7F142apxQOh+8Cf4AoUWhAQ=",
    "VersionHash": "fySDkHYy8/5IClNmEcPubrE3KEs="
  },
  "-33,-27": {
    "SourceVersionHash": "1Y7b7F142apxQOh+8Cf4AoUWhAQ=",
    "VersionHash": "fySDkHYy8/5IClNmEcPubrE3KEs="
  },
  "-33,-26": {
    "SourceVersionHash": "1Y7b7F142apxQOh+8Cf4AoUWhAQ=",
    "VersionHash": "fySDkHYy8/5IClNmEcPubrE3KEs="
  },
  "-34,-28": {
    "SourceVersionHash": "1Y7b7F142apxQOh+8Cf4AoUWhAQ=",
    "VersionHash": "fySDkHYy8/5IClNmEcPubrE3KEs="
  },
  "-35,-28": {
    "SourceVersionHash": "1Y7b7F142apxQOh+8Cf4AoUWhAQ=",
    "VersionHash": "fySDkHYy8/5IClNmEcPubrE3KEs="
  },
  "-33,-28": {
    "SourceVersionHash": "1Y7b7F142apxQOh+8Cf4AoUWhAQ=",
    "VersionHash": "fySDkHYy8/5IClNmEcPubrE3KEs="
  },
  "-35,-25": {
    "SourceVersionHash": "1Y7b7F142apxQOh+8Cf4AoUWhAQ=",
    "VersionHash": "fySDkHYy8/5IClNmEcPubrE3KEs="
  },
  "-34,-25": {
    "SourceVersionHash": "1Y7b7F142apxQOh+8Cf4AoUWhAQ=",
    "VersionHash": "fySDkHYy8/5IClNmEcPubrE3KEs="
  },
  "-36,-25": {
    "SourceVersionHash": "1Y7b7F142apxQOh+8Cf4AoUWhAQ=",
    "VersionHash": "fySDkHYy8/5IClNmEcPubrE3KEs="
  },
  "-33,-25": {
    "SourceVersionHash": "1Y7b7F142apxQOh+8Cf4AoUWhAQ=",
    "VersionHash": "fySDkHYy8/5IClNmEcPubrE3KEs="
  },
  "-36,-28": {
    "SourceVersionHash": "1Y7b7F142apxQOh+8Cf4AoUWhAQ=",
    "VersionHash": "fySDkHYy8/5IClNmEcPubrE3KEs="
  }
}